testfm/__init__.py
testfm/advanced.py
testfm/backup.py
testfm/base.py
testfm/decorators.py
testfm/factory.py
testfm/health.py
testfm/helpers.py
testfm/log.py
testfm/restore.py
testfm/service.py
testfm/upgrade.py
tests/__init__.py
tests/test_advanced.py
tests/test_backup.py
tests/test_health.py
tests/test_restore.py
tests/test_service.py
tests/test_upgrade.py
testfm-0.1.4.dist-info/LICENSE
testfm-0.1.4.dist-info/METADATA
testfm-0.1.4.dist-info/WHEEL
testfm-0.1.4.dist-info/top_level.txt
testfm-0.1.4.dist-info/RECORD
