Metadata-Version: 2.1
Name: testfm
Version: 0.1.4
Summary: TestFM is a test suite which exercises foreman-maintain tool.
Home-page: https://github.com/SatelliteQE/testfm
Author: Nikhil Kathole
Author-email: nikhilkathole2683@gmail.com
License: GNU GPL v3.0
Platform: UNKNOWN
Classifier: Intended Audience :: Developers
Classifier: License :: OSI Approved :: GNU General Public License v3 or later (GPLv3+)
Classifier: Natural Language :: English
Classifier: Programming Language :: Python :: 3
Requires-Dist: ansible
Requires-Dist: pytest-ansible
Requires-Dist: pytest
Requires-Dist: unittest2
